[
  {
    "key": "MESPAK01_0015_0000",
    "original": "ぶきのさくせい\nさいだいＨＰがあがる",
    "translation": "武器的制作\n最大HP上升",
    "stage": 0,
    "context": "机翻辅助：\n\n武器的制作\n最大HP上升\n\n最大HP上升"
  },
  {
    "key": "MESPAK01_0015_0001",
    "original": "ぶきのさくせい\nさいだいＨＰがあがる",
    "translation": "武器的制作\n最大HP上升",
    "stage": 0,
    "context": "机翻辅助：\n\n武器的制作\n最大HP上升\n\n最大HP上升"
  },
  {
    "key": "MESPAK01_0015_0002",
    "original": "ぶきのさくせい\nさいだいＨＰがあがる",
    "translation": "武器的制作\n最大HP上升",
    "stage": 0,
    "context": "机翻辅助：\n\n武器的制作\n最大HP上升\n\n最大HP上升"
  },
  {
    "key": "MESPAK01_0015_0003",
    "original": "ぶきのさくせい\nさいだいＨＰがあがる",
    "translation": "武器的制作\n最大HP上升",
    "stage": 0,
    "context": "机翻辅助：\n\n武器的制作\n最大HP上升\n\n最大HP上升"
  },
  {
    "key": "MESPAK01_0015_0004",
    "original": "ぶきのさくせい\nさいだいＨＰがあがる",
    "translation": "武器的制作\n最大HP上升",
    "stage": 0,
    "context": "机翻辅助：\n\n武器的制作\n最大HP上升\n\n最大HP上升"
  },
  {
    "key": "MESPAK01_0015_0005",
    "original": "ぼうぐのさくせい\nさいだいＭＰがあがる",
    "translation": "防具的制作\n最大MP的提高",
    "stage": 0,
    "context": "机翻辅助：\n\n防具的制作\n最大MP的提高\n\n最大MP上升"
  },
  {
    "key": "MESPAK01_0015_0006",
    "original": "ぼうぐのさくせい\nさいだいＭＰがあがる",
    "translation": "防具的制作\n最大MP的提高",
    "stage": 0,
    "context": "机翻辅助：\n\n防具的制作\n最大MP的提高\n\n最大MP上升"
  },
  {
    "key": "MESPAK01_0015_0007",
    "original": "ぼうぐのさくせい\nさいだいＭＰがあがる",
    "translation": "防具的制作\n最大MP的提高",
    "stage": 0,
    "context": "机翻辅助：\n\n防具的制作\n最大MP的提高\n\n最大MP上升"
  },
  {
    "key": "MESPAK01_0015_0008",
    "original": "ぼうぐのさくせい\nさいだいＭＰがあがる",
    "translation": "防具的制作\n最大MP的提高",
    "stage": 0,
    "context": "机翻辅助：\n\n防具的制作\n最大MP的提高\n\n最大MP上升"
  },
  {
    "key": "MESPAK01_0015_0009",
    "original": "ぼうぐのさくせい\nさいだいＭＰがあがる",
    "translation": "防具的制作\n最大MP的提高",
    "stage": 0,
    "context": "机翻辅助：\n\n防具的制作\n最大MP的提高\n\n最大MP上升"
  }
]