[
  {
    "key": "MESPAK04_0021_0000",
    "original": "せいしんを　むしばむ\nあくむの　チカラで\nこうげきする　★ねむり",
    "translation": "せいしんを　むしばむ\nあくむの　チカラで\nこうげきする　★ねむり",
    "stage": 1,
    "context": ""
  },
  {
    "key": "MESPAK04_0021_0001",
    "original": "セイなるヒカリの\nこうせんを　しせんの\nさきに　はなつ　★こんらん",
    "translation": "セイなるヒカリの\nこうせんを　しせんの\nさきに　はなつ　★こんらん",
    "stage": 1,
    "context": ""
  },
  {
    "key": "MESPAK04_0021_0002",
    "original": "すなを　はきだして\nみうごきを\nとれなくしてしまう",
    "translation": "すなを　はきだして\nみうごきを\nとれなくしてしまう",
    "stage": 1,
    "context": ""
  },
  {
    "key": "MESPAK04_0021_0003",
    "original": "ちでできた　しんくの\nムチをふるい　はげしく\nうちすえる　★ＨＰドレイン",
    "translation": "ちでできた　しんくの\nムチをふるい　はげしく\nうちすえる　★ＨＰドレイン",
    "stage": 1,
    "context": ""
  },
  {
    "key": "MESPAK04_0021_0004",
    "original": "セイなるチカラがこもった\nはなのくびかざりで\nステータスとＨＰをかいふく",
    "translation": "セイなるチカラがこもった\nはなのくびかざりで\nステータスとＨＰをかいふく",
    "stage": 1,
    "context": ""
  },
  {
    "key": "MESPAK04_0021_0005",
    "original": "セイなるヒカリをまとった\nパンチやキックで\nはげしい　さばきをくだす",
    "translation": "セイなるヒカリをまとった\nパンチやキックで\nはげしい　さばきをくだす",
    "stage": 1,
    "context": ""
  },
  {
    "key": "MESPAK04_0021_0006",
    "original": "ホウタイを　なげつけ\nキツく　しばりあげる",
    "translation": "ホウタイを　なげつけ\nキツく　しばりあげる",
    "stage": 1,
    "context": ""
  },
  {
    "key": "MESPAK04_0021_0007",
    "original": "体から　おうごんに\nかがやく　こうせんを\nはっしゃする　★デス",
    "translation": "体から　おうごんに\nかがやく　こうせんを\nはっしゃする　★デス",
    "stage": 1,
    "context": ""
  },
  {
    "key": "MESPAK04_0021_0008",
    "original": "ふででかいた　ノロイの\nことばを　はなち　データを\nぶんかいさせる　★デス",
    "translation": "ふででかいた　ノロイの\nことばを　はなち　データを\nぶんかいさせる　★デス",
    "stage": 1,
    "context": ""
  },
  {
    "key": "MESPAK04_0021_0009",
    "original": "おおきなおとを　だす\nハデなバクダンを　なげて\nバクハツさせる　★こてい",
    "translation": "おおきなおとを　だす\nハデなバクダンを　なげて\nバクハツさせる　★こてい",
    "stage": 1,
    "context": ""
  },
  {
    "key": "MESPAK04_0021_0010",
    "original": "ちょうのうりょくで\nうみだした　しょうげきはで\nこうげきする　★こんらん",
    "translation": "ちょうのうりょくで\nうみだした　しょうげきはで\nこうげきする　★こんらん",
    "stage": 1,
    "context": ""
  },
  {
    "key": "MESPAK04_0021_0011",
    "original": "こうねつの\nレーザービームを　はなち\nやきはらう",
    "translation": "こうねつの\nレーザービームを　はなち\nやきはらう",
    "stage": 1,
    "context": ""
  },
  {
    "key": "MESPAK04_0021_0012",
    "original": "体に　まとった\nリュウのオーラを\nこうそくで　はなつ",
    "translation": "体に　まとった\nリュウのオーラを\nこうそくで　はなつ",
    "stage": 1,
    "context": ""
  },
  {
    "key": "MESPAK04_0021_0013",
    "original": "やまねこの　しゅんびんな\nうごきから　くりだされる\nするどい　ツメのいちげき",
    "translation": "やまねこの　しゅんびんな\nうごきから　くりだされる\nするどい　ツメのいちげき",
    "stage": 1,
    "context": ""
  },
  {
    "key": "MESPAK04_0021_0014",
    "original": "セイなるじょうかのチカラが\nこもった　おたけびで\nデータぶんかいさせる",
    "translation": "セイなるじょうかのチカラが\nこもった　おたけびで\nデータぶんかいさせる",
    "stage": 1,
    "context": ""
  },
  {
    "key": "MESPAK04_0021_0015",
    "original": "りょうかたから　ヒカリの\nミサイルを　はっしゃして\nこうげきする",
    "translation": "りょうかたから　ヒカリの\nミサイルを　はっしゃして\nこうげきする",
    "stage": 1,
    "context": ""
  },
  {
    "key": "MESPAK04_0021_0016",
    "original": "いじげんのアナをうみだして\nまもりにりようし　みかたの\nぼうぎょりょくを　あげる",
    "translation": "いじげんのアナをうみだして\nまもりにりようし　みかたの\nぼうぎょりょくを　あげる",
    "stage": 1,
    "context": ""
  },
  {
    "key": "MESPAK04_0021_0017",
    "original": "りょうての　しゅりけんを\nバネのように　のばして\nきりさく",
    "translation": "りょうての　しゅりけんを\nバネのように　のばして\nきりさく",
    "stage": 1,
    "context": ""
  },
  {
    "key": "MESPAK04_0021_0018",
    "original": "ちからまかせに\nしゅういを　じならし\nしてしまう　★こてい",
    "translation": "ちからまかせに\nしゅういを　じならし\nしてしまう　★こてい",
    "stage": 1,
    "context": ""
  },
  {
    "key": "MESPAK04_0021_0019",
    "original": "そのばしょでおきた　かこの\nせんとうデータをよびだす\n★こてい★こんらん",
    "translation": "そのばしょでおきた　かこの\nせんとうデータをよびだす\n★こてい★こんらん",
    "stage": 1,
    "context": ""
  },
  {
    "key": "MESPAK04_0021_0020",
    "original": "セイなるかがやきを　まとい\nきょだいなカタナをつきたて\nとつげきし　りょうだんする",
    "translation": "セイなるかがやきを　まとい\nきょだいなカタナをつきたて\nとつげきし　りょうだんする",
    "stage": 1,
    "context": ""
  },
  {
    "key": "MESPAK04_0021_0021",
    "original": "わざヘルプ　みせってい\nボスてき　せんようわざ",
    "translation": "わざヘルプ　みせってい\nボスてき　せんようわざ",
    "stage": 1,
    "context": ""
  },
  {
    "key": "MESPAK04_0021_0022",
    "original": "わざヘルプ　みせってい\nボスてき　せんようわざ",
    "translation": "わざヘルプ　みせってい\nボスてき　せんようわざ",
    "stage": 1,
    "context": ""
  },
  {
    "key": "MESPAK04_0021_0026",
    "original": "きょうれつな　おんぱの\nたまの　しょうげきで\nこうげきする",
    "translation": "きょうれつな　おんぱの\nたまの　しょうげきで\nこうげきする",
    "stage": 1,
    "context": ""
  },
  {
    "key": "MESPAK04_0021_0027",
    "original": "きれあじばつぐんな\nメタルせいの　アームで\nきりつける　★まひ",
    "translation": "きれあじばつぐんな\nメタルせいの　アームで\nきりつける　★まひ",
    "stage": 1,
    "context": ""
  },
  {
    "key": "MESPAK04_0021_0028",
    "original": "キケンなヤミのチカラを\nこめたツメで\nきりさく　★どく",
    "translation": "キケンなヤミのチカラを\nこめたツメで\nきりさく　★どく",
    "stage": 1,
    "context": ""
  },
  {
    "key": "MESPAK04_0021_0029",
    "original": "ヤミのノロイが　こめられた\nアンコクの　ブレスをはいて\nこうげきする　★まひ",
    "translation": "ヤミのノロイが　こめられた\nアンコクの　ブレスをはいて\nこうげきする　★まひ",
    "stage": 1,
    "context": ""
  },
  {
    "key": "MESPAK04_0021_0030",
    "original": "つよく　もえさかる\nあおい　ホノオのたまを\nうちだして　こうげきする",
    "translation": "つよく　もえさかる\nあおい　ホノオのたまを\nうちだして　こうげきする",
    "stage": 1,
    "context": ""
  },
  {
    "key": "MESPAK04_0021_0031",
    "original": "するどい　トゲつきの\nてっきゅうを　たたきつけて\nこうげきする　★こんらん",
    "translation": "するどい　トゲつきの\nてっきゅうを　たたきつけて\nこうげきする　★こんらん",
    "stage": 1,
    "context": ""
  },
  {
    "key": "MESPAK04_0021_0032",
    "original": "エモノのチカラをすいとる\nあかいムチで　うちすえる\n★ＭＰドレイン★まひ",
    "translation": "エモノのチカラをすいとる\nあかいムチで　うちすえる\n★ＭＰドレイン★まひ",
    "stage": 1,
    "context": ""
  },
  {
    "key": "MESPAK04_0021_0033",
    "original": "カゼのように　すばやく\nするどい　キックを\nあびせる",
    "translation": "カゼのように　すばやく\nするどい　キックを\nあびせる",
    "stage": 1,
    "context": ""
  },
  {
    "key": "MESPAK04_0021_0034",
    "original": "しぜんの　しんぴのチカラで\nみかたの　ステータスと\nＨＰを　かいふく",
    "translation": "しぜんの　しんぴのチカラで\nみかたの　ステータスと\nＨＰを　かいふく",
    "stage": 1,
    "context": ""
  },
  {
    "key": "MESPAK04_0021_0035",
    "original": "どくのきりを　しゅういに\nはっしゃして\nこうげきする　★どく",
    "translation": "どくのきりを　しゅういに\nはっしゃして\nこうげきする　★どく",
    "stage": 1,
    "context": ""
  }
]