[
  {
    "key": "MESPAK03_0011_0000",
    "original": "Thank goodness! I'm saved!",
    "translation": "Thank goodness! I'm saved!",
    "stage": 1,
    "context": ""
  },
  {
    "key": "MESPAK03_0011_0001",
    "original": "I knew we could rely on you, Shuu♪",
    "translation": "I knew we could rely on you, Shuu♪",
    "stage": 1,
    "context": ""
  },
  {
    "key": "MESPAK03_0011_0002",
    "original": "Now that Shuu has opened up\nthe Gate,\nIt means that this DigiPort is now\nusable.\nSo why aren't you going back\nto the DigiBase...?",
    "translation": "Now that Shuu has opened up\nthe Gate,\nIt means that this DigiPort is now\nusable.\nSo why aren't you going back\nto the DigiBase...?",
    "stage": 1,
    "context": ""
  },
  {
    "key": "MESPAK03_0011_0003",
    "original": "It's impossible.",
    "translation": "It's impossible.",
    "stage": 1,
    "context": ""
  },
  {
    "key": "MESPAK03_0011_0004",
    "original": "What...?",
    "translation": "What...?",
    "stage": 1,
    "context": ""
  },
  {
    "key": "MESPAK03_0011_0005",
    "original": "Well you see, when the Bandits\ncaptured us...\nThey also stole the Black Box \nfrom the DigiShip!",
    "translation": "Well you see, when the Bandits\ncaptured us...\nThey also stole the Black Box \nfrom the DigiShip!",
    "stage": 1,
    "context": ""
  },
  {
    "key": "MESPAK03_0011_0006",
    "original": "I feel like I've heard of this \n'Black Box' somewhere before...\nIsn't that a very important part\nof the DigiShip...?",
    "translation": "I feel like I've heard of this \n'Black Box' somewhere before...\nIsn't that a very important part\nof the DigiShip...?",
    "stage": 1,
    "context": ""
  },
  {
    "key": "MESPAK03_0011_0007",
    "original": "It's extremely important!\nWithout the Black Box...\nThe DigiShip is unable to leave\nthis island!",
    "translation": "It's extremely important!\nWithout the Black Box...\nThe DigiShip is unable to leave\nthis island!",
    "stage": 1,
    "context": ""
  },
  {
    "key": "MESPAK03_0011_0008",
    "original": "Please, Shuu!\nGo and capture those Bandits,\nAnd take back our Black Box!",
    "translation": "Please, Shuu!\nGo and capture those Bandits,\nAnd take back our Black Box!",
    "stage": 1,
    "context": ""
  },
  {
    "key": "MESPAK03_0011_0009",
    "original": "It hasn't been long since we were\nlocked in here,\nSo they can't have gone too far!\n\nI'm counting on you, Shuu... Okay?",
    "translation": "It hasn't been long since we were\nlocked in here,\nSo they can't have gone too far!\n\nI'm counting on you, Shuu... Okay?",
    "stage": 1,
    "context": ""
  },
  {
    "key": "MESPAK03_0011_0010",
    "original": "Oh, Shuu!\nWelcome back!\nDid you find the Black Box??",
    "translation": "Oh, Shuu!\nWelcome back!\nDid you find the Black Box??",
    "stage": 1,
    "context": ""
  },
  {
    "key": "MESPAK03_0011_0011",
    "original": "T-that's fine! \nI'm sure you can handle it, Shuu!\nYou just gotta Momentai!",
    "translation": "T-that's fine! \nI'm sure you can handle it, Shuu!\nYou just gotta Momentai!",
    "stage": 1,
    "context": ""
  },
  {
    "key": "MESPAK03_0011_0012",
    "original": "Good luck, Shuu!",
    "translation": "Good luck, Shuu!",
    "stage": 1,
    "context": ""
  },
  {
    "key": "MESPAK03_0011_0013",
    "original": "Welcome back, Shuu!\nHow'd it go?\nWhat's that...?\nYou found Dos...?",
    "translation": "Welcome back, Shuu!\nHow'd it go?\nWhat's that...?\nYou found Dos...?",
    "stage": 1,
    "context": ""
  },
  {
    "key": "MESPAK03_0011_0014",
    "original": "Isn't Dos that skinny guy in the\nBandits group?\nHe's the most technologically\ninclined among the Bandits,\nSo I'm certain he's the one who\nstole the Black Box!",
    "translation": "Isn't Dos that skinny guy in the\nBandits group?\nHe's the most technologically\ninclined among the Bandits,\nSo I'm certain he's the one who\nstole the Black Box!",
    "stage": 1,
    "context": ""
  },
  {
    "key": "MESPAK03_0011_0015",
    "original": "But isn't it kinda strange...?",
    "translation": "But isn't it kinda strange...?",
    "stage": 1,
    "context": ""
  },
  {
    "key": "MESPAK03_0011_0016",
    "original": "Why would he be loitering around\nhere instead of escaping...?\nAnd all on his own, at that...",
    "translation": "Why would he be loitering around\nhere instead of escaping...?\nAnd all on his own, at that...",
    "stage": 1,
    "context": ""
  },
  {
    "key": "MESPAK03_0011_0017",
    "original": "It's most likely Uno and Tres\nare nearby, too...",
    "translation": "It's most likely Uno and Tres\nare nearby, too...",
    "stage": 1,
    "context": ""
  },
  {
    "key": "MESPAK03_0011_0018",
    "original": "If that's the case, then their \nintentions are pretty clear.\nThey probably intend to steal\nsomething else from us, too.",
    "translation": "If that's the case, then their \nintentions are pretty clear.\nThey probably intend to steal\nsomething else from us, too.",
    "stage": 1,
    "context": ""
  },
  {
    "key": "MESPAK03_0011_0019",
    "original": "W-what should we do??\nWe can't run from here right now!",
    "translation": "W-what should we do??\nWe can't run from here right now!",
    "stage": 1,
    "context": ""
  },
  {
    "key": "MESPAK03_0011_0020",
    "original": "Don't worry about it, \njust Momentaiii!",
    "translation": "Don't worry about it, \njust Momentaiii!",
    "stage": 1,
    "context": ""
  },
  {
    "key": "MESPAK03_0011_0021",
    "original": "Those Bandits aren't a problem, so\nlong as Shuu is around!\nAfter all, Shuu is the best Tamer \nthere is!",
    "translation": "Those Bandits aren't a problem, so\nlong as Shuu is around!\nAfter all, Shuu is the best Tamer \nthere is!",
    "stage": 1,
    "context": ""
  },
  {
    "key": "MESPAK03_0011_0022",
    "original": "Y-y-you're right! I'm sure!\nShuu will be totally fine...!\nThere's not a single Tamer that\ncan stand up to Shuu!",
    "translation": "Y-y-you're right! I'm sure!\nShuu will be totally fine...!\nThere's not a single Tamer that\ncan stand up to Shuu!",
    "stage": 1,
    "context": ""
  },
  {
    "key": "MESPAK03_0011_0023",
    "original": "I believe the one with the Black Box\nis most likely their leader, Uno.\nIf you follow Dos, I'm sure you'll\nbe able to find Uno, too.",
    "translation": "I believe the one with the Black Box\nis most likely their leader, Uno.\nIf you follow Dos, I'm sure you'll\nbe able to find Uno, too.",
    "stage": 1,
    "context": ""
  },
  {
    "key": "MESPAK03_0011_0024",
    "original": "Good luck, Shuu!",
    "translation": "Good luck, Shuu!",
    "stage": 1,
    "context": ""
  },
  {
    "key": "MESPAK03_0011_0025",
    "original": "Welcome back, Shuu!\nDid you find those Bandits?!\nWhat...? You haven't yet...?\n\nBut I'm sure you should find Uno\nif you just follow after Dos...",
    "translation": "Welcome back, Shuu!\nDid you find those Bandits?!\nWhat...? You haven't yet...?\n\nBut I'm sure you should find Uno\nif you just follow after Dos...",
    "stage": 1,
    "context": ""
  },
  {
    "key": "MESPAK03_0011_0026",
    "original": "Please, Shuu!\nYou've gotta go find them!\nFind them and get our Black Box\nback!",
    "translation": "Please, Shuu!\nYou've gotta go find them!\nFind them and get our Black Box\nback!",
    "stage": 1,
    "context": ""
  },
  {
    "key": "MESPAK03_0011_0027",
    "original": "Looks like a strange uninvited\nguest has shown up...\nI've got a bad feeling about this...\nI'd better contact Tres.",
    "translation": "Looks like a strange uninvited\nguest has shown up...\nI've got a bad feeling about this...\nI'd better contact Tres.",
    "stage": 1,
    "context": ""
  },
  {
    "key": "MESPAK03_0011_0028",
    "original": "Hey, Tres! Respond quickly.\nThis isn't good.\nThat twerp Tamer is loitering \naround the DigiPort...\nI can't get to the energy\nconnector with him hanging around.\nCould you go distract him for me?",
    "translation": "Hey, Tres! Respond quickly.\nThis isn't good.\nThat twerp Tamer is loitering \naround the DigiPort...\nI can't get to the energy\nconnector with him hanging around.\nCould you go distract him for me?",
    "stage": 1,
    "context": ""
  },
  {
    "key": "MESPAK03_0011_0029",
    "original": "Why do I have to go...?\n\nWhy can't you deal with both \nproblems at the same time??\nWhich reminds me, \nI hope you didn't forget, Dos...\nIf you lose to that kid this time,\nyou're getting a nice, shaved head!",
    "translation": "Why do I have to go...?\n\nWhy can't you deal with both \nproblems at the same time??\nWhich reminds me, \nI hope you didn't forget, Dos...\nIf you lose to that kid this time,\nyou're getting a nice, shaved head!",
    "stage": 1,
    "context": ""
  },
  {
    "key": "MESPAK03_0011_0030",
    "original": ".........\nOuch! Ow, ow, ow, ow...\nMy stomach suddenly started \nhurting really bad!",
    "translation": ".........\nOuch! Ow, ow, ow, ow...\nMy stomach suddenly started \nhurting really bad!",
    "stage": 1,
    "context": ""
  },
  {
    "key": "MESPAK03_0011_0031",
    "original": "What kind of excuse is that?!\nStop running and start fighting!",
    "translation": "What kind of excuse is that?!\nStop running and start fighting!",
    "stage": 1,
    "context": ""
  },
  {
    "key": "MESPAK03_0011_0032",
    "original": "My head is hurting a lot, too,,,\nI'd better retreat for now!",
    "translation": "My head is hurting a lot, too,,,\nI'd better retreat for now!",
    "stage": 1,
    "context": ""
  },
  {
    "key": "MESPAK03_0011_0033",
    "original": "It would be such a simple matter to\ntake that kid down,\nIt's just such a pity my stomach \nsuddenly started acting up...!\nLooks like I've also escaped having\nmy head shaven, too...!",
    "translation": "It would be such a simple matter to\ntake that kid down,\nIt's just such a pity my stomach \nsuddenly started acting up...!\nLooks like I've also escaped having\nmy head shaven, too...!",
    "stage": 1,
    "context": ""
  },
  {
    "key": "MESPAK03_0011_0034",
    "original": "Fine, fine, I get it.\n\nYou would have won if you did fight\nthem, I know.",
    "translation": "Fine, fine, I get it.\n\nYou would have won if you did fight\nthem, I know.",
    "stage": 1,
    "context": ""
  },
  {
    "key": "MESPAK03_0011_0035",
    "original": "...So why don't you go ahead and\nfight them?",
    "translation": "...So why don't you go ahead and\nfight them?",
    "stage": 1,
    "context": ""
  },
  {
    "key": "MESPAK03_0011_0036",
    "original": "Y-y-y-you followed me all this\nway...?!\nYou stalker!\nPolice! Come quick!",
    "translation": "Y-y-y-you followed me all this\nway...?!\nYou stalker!\nPolice! Come quick!",
    "stage": 1,
    "context": ""
  },
  {
    "key": "MESPAK03_0011_0037",
    "original": "...What's with that dumb act?\nJust give it up already.",
    "translation": "...What's with that dumb act?\nJust give it up already.",
    "stage": 1,
    "context": ""
  },
  {
    "key": "MESPAK03_0011_0038",
    "original": "I-I-I-I have no problem fighting\nthem, but...\nLadies first... isn't that right...?",
    "translation": "I-I-I-I have no problem fighting\nthem, but...\nLadies first... isn't that right...?",
    "stage": 1,
    "context": ""
  },
  {
    "key": "MESPAK03_0011_0039",
    "original": "Argh, alright, enough already with\nyour complaining.\nI'll just have to beat some sense\ninto you myself!",
    "translation": "Argh, alright, enough already with\nyour complaining.\nI'll just have to beat some sense\ninto you myself!",
    "stage": 1,
    "context": ""
  },
  {
    "key": "MESPAK03_0011_0040",
    "original": "Fine then, I'll do it!\nI've made up my mind!\nWell, not really...\nBut I'll do it, anyway!\nI'll show you how a real man\ndoes things!",
    "translation": "Fine then, I'll do it!\nI've made up my mind!\nWell, not really...\nBut I'll do it, anyway!\nI'll show you how a real man\ndoes things!",
    "stage": 1,
    "context": ""
  },
  {
    "key": "MESPAK03_0011_0041",
    "original": "If spirit alone was all that was \nneeded to win,\nLife would be a lot easier,\ndon't you think?\nNow then, have you learned your\nlesson, boys and girls?\nIn a situation like this, the best \noption is to...\nRETREAT!",
    "translation": "If spirit alone was all that was \nneeded to win,\nLife would be a lot easier,\ndon't you think?\nNow then, have you learned your\nlesson, boys and girls?\nIn a situation like this, the best \noption is to...\nRETREAT!",
    "stage": 1,
    "context": ""
  },
  {
    "key": "MESPAK03_0011_0042",
    "original": "I'm sure they've learned a pretty\nvaluable lesson,\nThat being not to judge a Tamer's\nability by looks alone.\nAnd that good-for-nothing losers\nwill always remain that way...\nBut remember this...\nNo matter how powerful you are,\nWorking alone will only get you\nso far, you got that?",
    "translation": "I'm sure they've learned a pretty\nvaluable lesson,\nThat being not to judge a Tamer's\nability by looks alone.\nAnd that good-for-nothing losers\nwill always remain that way...\nBut remember this...\nNo matter how powerful you are,\nWorking alone will only get you\nso far, you got that?",
    "stage": 1,
    "context": ""
  },
  {
    "key": "MESPAK03_0011_0043",
    "original": "What??\nI don't get it at all!\nWhat does all this have to do with\ngettin' the connector?!",
    "translation": "What??\nI don't get it at all!\nWhat does all this have to do with\ngettin' the connector?!",
    "stage": 1,
    "context": ""
  },
  {
    "key": "MESPAK03_0011_0044",
    "original": "That's not the issue here...\n\nThat boy was trying to escape, \nbut my stomach got messed up,\nAnd then I started getting a\nheadache, and...",
    "translation": "That's not the issue here...\n\nThat boy was trying to escape, \nbut my stomach got messed up,\nAnd then I started getting a\nheadache, and...",
    "stage": 1,
    "context": ""
  },
  {
    "key": "MESPAK03_0011_0045",
    "original": "Shut it! I have no clue what \nyou're goin' on about!\nI'm the one who'll be gettin' a\nheadache listenin' to all that!",
    "translation": "Shut it! I have no clue what \nyou're goin' on about!\nI'm the one who'll be gettin' a\nheadache listenin' to all that!",
    "stage": 1,
    "context": ""
  },
  {
    "key": "MESPAK03_0011_0046",
    "original": "Aw man...\nCan't the DigiShip hurry it up...?\nI don't like getting all dirty.",
    "translation": "Aw man...\nCan't the DigiShip hurry it up...?\nI don't like getting all dirty.",
    "stage": 1,
    "context": ""
  },
  {
    "key": "MESPAK03_0011_0047",
    "original": "Oh my... more importantly, it looks \nlike that Tamer has come back.",
    "translation": "Oh my... more importantly, it looks \nlike that Tamer has come back.",
    "stage": 1,
    "context": ""
  },
  {
    "key": "MESPAK03_0011_0048",
    "original": "What?! This guy!\nHe chased us all the way here?!",
    "translation": "What?! This guy!\nHe chased us all the way here?!",
    "stage": 1,
    "context": ""
  },
  {
    "key": "MESPAK03_0011_0049",
    "original": "Ugh... Of all people...\nIt had to be you again...?!",
    "translation": "Ugh... Of all people...\nIt had to be you again...?!",
    "stage": 1,
    "context": ""
  },
  {
    "key": "MESPAK03_0011_0050",
    "original": "You want the Black Box back?\nEnough of your whinin'!\nIf we were plannin' on giving it \nback that easily,\nWe wouldn't have bothered takin'\nit in the first place!",
    "translation": "You want the Black Box back?\nEnough of your whinin'!\nIf we were plannin' on giving it \nback that easily,\nWe wouldn't have bothered takin'\nit in the first place!",
    "stage": 1,
    "context": ""
  },
  {
    "key": "MESPAK03_0011_0051",
    "original": "Right now, we really, truly need \nthat Black Box!\nWith that Box, as well as the \nenergy connector...\nWe can get all the Lost Digimon\nto the Real World...!",
    "translation": "Right now, we really, truly need \nthat Black Box!\nWith that Box, as well as the \nenergy connector...\nWe can get all the Lost Digimon\nto the Real World...!",
    "stage": 1,
    "context": ""
  },
  {
    "key": "MESPAK03_0011_0052",
    "original": "Be quiet, Dos. \nThat has nothin' to do with him.\nAnd I couldn't care less what he \nplans to do, either.\nAll that matters is he's in the way,\nand he needs to get lost.",
    "translation": "Be quiet, Dos. \nThat has nothin' to do with him.\nAnd I couldn't care less what he \nplans to do, either.\nAll that matters is he's in the way,\nand he needs to get lost.",
    "stage": 1,
    "context": ""
  },
  {
    "key": "MESPAK03_0011_0053",
    "original": "And if you've got a problem with\nthat, then go ahead and stop me.\nThat's the way of the Digital World!",
    "translation": "And if you've got a problem with\nthat, then go ahead and stop me.\nThat's the way of the Digital World!",
    "stage": 1,
    "context": ""
  },
  {
    "key": "MESPAK03_0011_0054",
    "original": "What? You actually want to fight?\nAren't you a unique one.",
    "translation": "What? You actually want to fight?\nAren't you a unique one.",
    "stage": 1,
    "context": ""
  },
  {
    "key": "MESPAK03_0011_0055",
    "original": "Well that's fine and all, but what \nif you really do lose to him?\nDon't tell me you'll actually return\nthe Black Box to them...\n...Will you?",
    "translation": "Well that's fine and all, but what \nif you really do lose to him?\nDon't tell me you'll actually return\nthe Black Box to them...\n...Will you?",
    "stage": 1,
    "context": ""
  },
  {
    "key": "MESPAK03_0011_0056",
    "original": "Gimme a break here...\n\nIf we return this box, all our work\nuntil now will be for naught!\nAll we need to do is defeat this kid\nand make a run for it, right??",
    "translation": "Gimme a break here...\n\nIf we return this box, all our work\nuntil now will be for naught!\nAll we need to do is defeat this kid\nand make a run for it, right??",
    "stage": 1,
    "context": ""
  },
  {
    "key": "MESPAK03_0011_0057",
    "original": "...Yeah, you're right.\n\nWe've only made it this far \nbecause we've been like this.\nBut it's such a pain to have to\nsneak and run away all the time!\nJust think about it for a minute.\n\nCan you just run away from a \nfight you, yourself, started?!",
    "translation": "...Yeah, you're right.\n\nWe've only made it this far \nbecause we've been like this.\nBut it's such a pain to have to\nsneak and run away all the time!\nJust think about it for a minute.\n\nCan you just run away from a \nfight you, yourself, started?!",
    "stage": 1,
    "context": ""
  },
  {
    "key": "MESPAK03_0011_0058",
    "original": "If he somehow manages to win\nagainst me, he can have the Box.\nAnd no one has any right to \ncomplain about that,\nBecause I will not lose!",
    "translation": "If he somehow manages to win\nagainst me, he can have the Box.\nAnd no one has any right to \ncomplain about that,\nBecause I will not lose!",
    "stage": 1,
    "context": ""
  },
  {
    "key": "MESPAK03_0011_0059",
    "original": ".........\n\nWell I guess it would be pretty cool\nto actually see you win for once.",
    "translation": ".........\n\nWell I guess it would be pretty cool\nto actually see you win for once.",
    "stage": 1,
    "context": ""
  },
  {
    "key": "MESPAK03_0011_0060",
    "original": "You're a man, too, aren't you?!\n\nA man can only look ahead,\nthere's no option to run away!",
    "translation": "You're a man, too, aren't you?!\n\nA man can only look ahead,\nthere's no option to run away!",
    "stage": 1,
    "context": ""
  },
  {
    "key": "MESPAK03_0011_0061",
    "original": "Say all you want, but it'll all be\npointless if you lose!",
    "translation": "Say all you want, but it'll all be\npointless if you lose!",
    "stage": 1,
    "context": ""
  },
  {
    "key": "MESPAK03_0011_0062",
    "original": "Shut up!\nLook who's talkin'!\nDidn't you also lose to this same\nkid earlier?!\nDon't go lookin' down on me so \nsmug with that huge nose of yours!",
    "translation": "Shut up!\nLook who's talkin'!\nDidn't you also lose to this same\nkid earlier?!\nDon't go lookin' down on me so \nsmug with that huge nose of yours!",
    "stage": 1,
    "context": ""
  },
  {
    "key": "MESPAK03_0011_0063",
    "original": "These two really are completely\nbeyond help.\nWhy must all men be such idiots...",
    "translation": "These two really are completely\nbeyond help.\nWhy must all men be such idiots...",
    "stage": 1,
    "context": ""
  },
  {
    "key": "MESPAK03_0011_0064",
    "original": "Alright! The DigiShip's here,\nPlaytime's over!\nIf you don't hurry, I'll leave the \nboth of you behind!",
    "translation": "Alright! The DigiShip's here,\nPlaytime's over!\nIf you don't hurry, I'll leave the \nboth of you behind!",
    "stage": 1,
    "context": ""
  },
  {
    "key": "MESPAK03_0011_0065",
    "original": "H-hey Tres, wait a minute...!",
    "translation": "H-hey Tres, wait a minute...!",
    "stage": 1,
    "context": ""
  },
  {
    "key": "MESPAK03_0011_0066",
    "original": "...Hmph.\n\nThis was our last chance to escape\nthis place...\nBut I guess that's how things are,\nI'll have to think of another way.",
    "translation": "...Hmph.\n\nThis was our last chance to escape\nthis place...\nBut I guess that's how things are,\nI'll have to think of another way.",
    "stage": 1,
    "context": ""
  },
  {
    "key": "MESPAK03_0011_0067",
    "original": "Obtained a Key Item!\n^i",
    "translation": "Obtained a Key Item!\n^i",
    "stage": 1,
    "context": ""
  },
  {
    "key": "MESPAK03_0011_0068",
    "original": "I'll let you go this time, but next \ntime you won't be so lucky!\nDon't forget that!",
    "translation": "I'll let you go this time, but next \ntime you won't be so lucky!\nDon't forget that!",
    "stage": 1,
    "context": ""
  },
  {
    "key": "MESPAK03_0011_0069",
    "original": "Oh, Shuu!\nDid you find the Bandits??\nI was worried because we couldn't\nget in contact with you...\n...What?\nYou found the Black Box??\nYou got it back? \nFrom the Bandits??\nH-how on earth did you...\nYou defeated them?!\nB-both of them?!?\nWhaaat???\nThat's unbelieveable!\nYou're incredible, Shuu!\nThanks to you, we can finally\nreturn to the DigiBase!\nWe'll be waiting for you\nat the DigiPort♪",
    "translation": "Oh, Shuu!\nDid you find the Bandits??\nI was worried because we couldn't\nget in contact with you...\n...What?\nYou found the Black Box??\nYou got it back? \nFrom the Bandits??\nH-how on earth did you...\nYou defeated them?!\nB-both of them?!?\nWhaaat???\nThat's unbelieveable!\nYou're incredible, Shuu!\nThanks to you, we can finally\nreturn to the DigiBase!\nWe'll be waiting for you\nat the DigiPort♪",
    "stage": 1,
    "context": ""
  },
  {
    "key": "MESPAK03_0011_0070",
    "original": "The trial version ends here.\n\nThanks for playing!",
    "translation": "The trial version ends here.\n\nThanks for playing!",
    "stage": 1,
    "context": ""
  },
  {
    "key": "MESPAK03_0011_0071",
    "original": ".........\nWell, a win is a win, I guess.\nBut we did act pretty desperate\nand immature...",
    "translation": ".........\nWell, a win is a win, I guess.\nBut we did act pretty desperate\nand immature...",
    "stage": 1,
    "context": ""
  },
  {
    "key": "MESPAK03_0011_0072",
    "original": "You've gotta be kiddin' me?! Can't\nyou see how strong this kid is?!\nWe'll never stand a chance if we're\nso concerned about how we look!\nOn top of that, when we lose, all\nyou do is complain!\nIsn't that right, you pathetic loser?",
    "translation": "You've gotta be kiddin' me?! Can't\nyou see how strong this kid is?!\nWe'll never stand a chance if we're\nso concerned about how we look!\nOn top of that, when we lose, all\nyou do is complain!\nIsn't that right, you pathetic loser?",
    "stage": 1,
    "context": ""
  },
  {
    "key": "MESPAK03_0011_0073",
    "original": "Jeez... \nAnd what's with that smug look...\nIt makes me feel uneasy...",
    "translation": "Jeez... \nAnd what's with that smug look...\nIt makes me feel uneasy...",
    "stage": 1,
    "context": ""
  },
  {
    "key": "MESPAK03_0011_0074",
    "original": "Shut it! \nNo matter how cool you try to look,\nIt doesn't mean anything if you \ncan't win!\nBesides, not only are you uncool,\nbut you're always a loser, too!\nYou're the worst of the worst!\nJust quit the Bandits, already!",
    "translation": "Shut it! \nNo matter how cool you try to look,\nIt doesn't mean anything if you \ncan't win!\nBesides, not only are you uncool,\nbut you're always a loser, too!\nYou're the worst of the worst!\nJust quit the Bandits, already!",
    "stage": 1,
    "context": ""
  },
  {
    "key": "MESPAK03_0011_0075",
    "original": "The both of you look uncool \nregardless if you're winning or not.\nPlus...\nI'm the one who wants to quit...",
    "translation": "The both of you look uncool \nregardless if you're winning or not.\nPlus...\nI'm the one who wants to quit...",
    "stage": 1,
    "context": ""
  },
  {
    "key": "MESPAK03_0011_0076",
    "original": "Alright! The DigiShip's here,\nPlaytime's over!\nIf you don't hurry, I'll leave the \nboth of you behind!",
    "translation": "Alright! The DigiShip's here,\nPlaytime's over!\nIf you don't hurry, I'll leave the \nboth of you behind!",
    "stage": 1,
    "context": ""
  },
  {
    "key": "MESPAK03_0011_0077",
    "original": "H-hey Tres, wait a minute...!",
    "translation": "H-hey Tres, wait a minute...!",
    "stage": 1,
    "context": ""
  },
  {
    "key": "MESPAK03_0011_0078",
    "original": "...Hmph.\n\nThis was our last chance to escape\nthis place...\nBut I guess thats how things are,\nI'll have to think of another way.",
    "translation": "...Hmph.\n\nThis was our last chance to escape\nthis place...\nBut I guess thats how things are,\nI'll have to think of another way.",
    "stage": 1,
    "context": ""
  },
  {
    "key": "MESPAK03_0011_0079",
    "original": "Obtained a Key Item!\n^i",
    "translation": "Obtained a Key Item!\n^i",
    "stage": 1,
    "context": ""
  },
  {
    "key": "MESPAK03_0011_0080",
    "original": "This is the only time we'll hand over\nsomethin' so easily like this.\nThe Digital World ain't such a\nforgivin' place, you got that?\nYou better remember it!",
    "translation": "This is the only time we'll hand over\nsomethin' so easily like this.\nThe Digital World ain't such a\nforgivin' place, you got that?\nYou better remember it!",
    "stage": 1,
    "context": ""
  },
  {
    "key": "MESPAK03_0011_0081",
    "original": "Oh, Shuu!\nDid you find the Bandits??\nI was worried because we couldn't\nget in contact with you...\n...What?\nYou found the Black Box??\nYou got it back? \nFrom the Bandits??\nH-how on earth did you...\nYou defeated them?!\nB-both of them?!?\nWhaaat???\nThat's unbelieveable!\nYou're incredible, Shuu!\nThanks to you, we can finally\nreturn to the DigiBase!\nWe'll be waiting for you\nat the DigiPort♪",
    "translation": "Oh, Shuu!\nDid you find the Bandits??\nI was worried because we couldn't\nget in contact with you...\n...What?\nYou found the Black Box??\nYou got it back? \nFrom the Bandits??\nH-how on earth did you...\nYou defeated them?!\nB-both of them?!?\nWhaaat???\nThat's unbelieveable!\nYou're incredible, Shuu!\nThanks to you, we can finally\nreturn to the DigiBase!\nWe'll be waiting for you\nat the DigiPort♪",
    "stage": 1,
    "context": ""
  },
  {
    "key": "MESPAK03_0011_0082",
    "original": "The trial version ends here.\n\nThanks for playing!",
    "translation": "The trial version ends here.\n\nThanks for playing!",
    "stage": 1,
    "context": ""
  },
  {
    "key": "MESPAK03_0011_0083",
    "original": "Hey, Shuu, isn't the Palette Key\naround here somewhere?\nHurry and open the Port Gate!",
    "translation": "Hey, Shuu, isn't the Palette Key\naround here somewhere?\nHurry and open the Port Gate!",
    "stage": 1,
    "context": ""
  },
  {
    "key": "MESPAK03_0011_0084",
    "original": "Shuu, you're going the wrong way!\n\nHurry and come this way!",
    "translation": "Shuu, you're going the wrong way!\n\nHurry and come this way!",
    "stage": 1,
    "context": ""
  },
  {
    "key": "MESPAK03_0011_0085",
    "original": "Are you okay, Shuu?\nDon't worry, Momentai!\nEveryone fails once in a while, okay?\n\nIt's not important whether you win\nor lose,\nWhat's important is that you never\ngive up!",
    "translation": "Are you okay, Shuu?\nDon't worry, Momentai!\nEveryone fails once in a while, okay?\n\nIt's not important whether you win\nor lose,\nWhat's important is that you never\ngive up!",
    "stage": 1,
    "context": ""
  },
  {
    "key": "MESPAK03_0011_0086",
    "original": "Your DigiFarm would be much\nlivelier with some Digimon in it.\nYou can have your Digimon in the\nDigiLab create Weapons and Armor,\nAs well as let them undergo \ntraining!",
    "translation": "Your DigiFarm would be much\nlivelier with some Digimon in it.\nYou can have your Digimon in the\nDigiLab create Weapons and Armor,\nAs well as let them undergo \ntraining!",
    "stage": 1,
    "context": ""
  },
  {
    "key": "MESPAK03_0011_0087",
    "original": "You can alter a lot of things about\nthe DigiFarm.\nBe sure to create a Farm that suits\nyour particular Digimon, got it?",
    "translation": "You can alter a lot of things about\nthe DigiFarm.\nBe sure to create a Farm that suits\nyour particular Digimon, got it?",
    "stage": 1,
    "context": ""
  },
  {
    "key": "MESPAK03_0011_0088",
    "original": "The DigiBase is basically like\na base camp.\nEverything a Tamer needs can be\nfound right here.\nYou also return here when you are\ndefeated in battle.",
    "translation": "The DigiBase is basically like\na base camp.\nEverything a Tamer needs can be\nfound right here.\nYou also return here when you are\ndefeated in battle.",
    "stage": 1,
    "context": ""
  },
  {
    "key": "MESPAK03_0011_0089",
    "original": "There used to be other Tamers\nhere too, a long time ago.\nBut now there's only Digimon.",
    "translation": "There used to be other Tamers\nhere too, a long time ago.\nBut now there's only Digimon.",
    "stage": 1,
    "context": ""
  },
  {
    "key": "MESPAK03_0011_0090",
    "original": "Requests from Digimon are \ndelivered to your Quest PC.\nI wonder if you've received a lot\nof requests yet?\nIt's a Tamer's duty to fufill those\nrequests!",
    "translation": "Requests from Digimon are \ndelivered to your Quest PC.\nI wonder if you've received a lot\nof requests yet?\nIt's a Tamer's duty to fufill those\nrequests!",
    "stage": 1,
    "context": ""
  },
  {
    "key": "MESPAK03_0011_0091",
    "original": "Up ahead is the DigiPort, where\nthe DigiShip docks.\nOnce you've got a DigiShip,\n\nYou can go to other DigiPorts from\nhere in an instant!\nAs long as you've got the address,\nyou can go wherever you want!\nYou can find DigiPorts in all sorts\nof areas,\nSo don't forget to open any gates\nyou see right away, got it?",
    "translation": "Up ahead is the DigiPort, where\nthe DigiShip docks.\nOnce you've got a DigiShip,\n\nYou can go to other DigiPorts from\nhere in an instant!\nAs long as you've got the address,\nyou can go wherever you want!\nYou can find DigiPorts in all sorts\nof areas,\nSo don't forget to open any gates\nyou see right away, got it?",
    "stage": 1,
    "context": ""
  },
  {
    "key": "MESPAK03_0011_0092",
    "original": "We need the Evolution Tree in \norder to Digivolve.\nIf you insert the Plates you get\nby repairing them with the tools,\nYou'll unlock more and more\nDigivolution options!\nI hope the Evolution Tree gets \ncompleted soon...!",
    "translation": "We need the Evolution Tree in \norder to Digivolve.\nIf you insert the Plates you get\nby repairing them with the tools,\nYou'll unlock more and more\nDigivolution options!\nI hope the Evolution Tree gets \ncompleted soon...!",
    "stage": 1,
    "context": ""
  },
  {
    "key": "MESPAK03_0011_0093",
    "original": "Your DigiReport has arrived!\nWould you like to see it?",
    "translation": "Your DigiReport has arrived!\nWould you like to see it?",
    "stage": 1,
    "context": ""
  },
  {
    "key": "MESPAK03_0011_0094",
    "original": "Yes",
    "translation": "Yes",
    "stage": 1,
    "context": ""
  },
  {
    "key": "MESPAK03_0011_0095",
    "original": "No",
    "translation": "No",
    "stage": 1,
    "context": ""
  },
  {
    "key": "MESPAK03_0011_0096",
    "original": "Obtained a Consumable Item!\n^0",
    "translation": "Obtained a Consumable Item!\n^0",
    "stage": 1,
    "context": ""
  },
  {
    "key": "MESPAK03_0011_0097",
    "original": "Obtained Consumable Items!\n^0　×^1",
    "translation": "Obtained Consumable Items!\n^0　×^1",
    "stage": 1,
    "context": ""
  },
  {
    "key": "MESPAK03_0011_0098",
    "original": "Obtained a piece of Equipment!\n^0",
    "translation": "Obtained a piece of Equipment!\n^0",
    "stage": 1,
    "context": ""
  },
  {
    "key": "MESPAK03_0011_0099",
    "original": "Obtained Equipment!\n^0　×^1",
    "translation": "Obtained Equipment!\n^0　×^1",
    "stage": 1,
    "context": ""
  },
  {
    "key": "MESPAK03_0011_0100",
    "original": "Obtained a Bug Plate!\n^0",
    "translation": "Obtained a Bug Plate!\n^0",
    "stage": 1,
    "context": ""
  },
  {
    "key": "MESPAK03_0011_0101",
    "original": "Obtained Bug Plates!\n^0　×^1",
    "translation": "Obtained Bug Plates!\n^0　×^1",
    "stage": 1,
    "context": ""
  },
  {
    "key": "MESPAK03_0011_0102",
    "original": "Obtained Farm Goods!\n^0",
    "translation": "Obtained Farm Goods!\n^0",
    "stage": 1,
    "context": ""
  },
  {
    "key": "MESPAK03_0011_0103",
    "original": "Obtained Farm Goods!\n^0　×^1",
    "translation": "Obtained Farm Goods!\n^0　×^1",
    "stage": 1,
    "context": ""
  },
  {
    "key": "MESPAK03_0011_0104",
    "original": "Obtained a DigiPlate!\n^0",
    "translation": "Obtained a DigiPlate!\n^0",
    "stage": 1,
    "context": ""
  },
  {
    "key": "MESPAK03_0011_0105",
    "original": "Obtained a Key Item!\n^0",
    "translation": "Obtained a Key Item!\n^0",
    "stage": 1,
    "context": ""
  },
  {
    "key": "MESPAK03_0011_0106",
    "original": "Obtained ^1 bits!",
    "translation": "Obtained ^1 bits!",
    "stage": 1,
    "context": ""
  },
  {
    "key": "MESPAK03_0011_0107",
    "original": "Obtained ^1 Tamer Points!",
    "translation": "Obtained ^1 Tamer Points!",
    "stage": 1,
    "context": ""
  },
  {
    "key": "MESPAK03_0011_0108",
    "original": "Quest Cleared!",
    "translation": "Quest Cleared!",
    "stage": 1,
    "context": ""
  },
  {
    "key": "MESPAK03_0011_0109",
    "original": "Are you ^P?\n\nWell, you see, I lost some very\nvaluable goods...\nHave you heard about \n'Farm Goods'?\nThey're important item used to\ntrain Digimon in the Farm.\nBut I must have dropped them\nsomewhere in Chip Forest.\nI'll make it worth your while if\nyou can go find them for me.\nSo could you go take a look?\n\nThat's right!\n\nI'd better give you the address \nof the Chip Forest's DigiPort!\n",
    "translation": "Are you ^P?\n\nWell, you see, I lost some very\nvaluable goods...\nHave you heard about \n'Farm Goods'?\nThey're important item used to\ntrain Digimon in the Farm.\nBut I must have dropped them\nsomewhere in Chip Forest.\nI'll make it worth your while if\nyou can go find them for me.\nSo could you go take a look?\n\nThat's right!\n\nI'd better give you the address \nof the Chip Forest's DigiPort!\n",
    "stage": 1,
    "context": ""
  },
  {
    "key": "MESPAK03_0011_0110",
    "original": "Obtained a Key Item!\nChip Forest Address",
    "translation": "Obtained a Key Item!\nChip Forest Address",
    "stage": 1,
    "context": ""
  },
  {
    "key": "MESPAK03_0011_0111",
    "original": "With that, you can now fly there\nusing the DigiShip.",
    "translation": "With that, you can now fly there\nusing the DigiShip.",
    "stage": 1,
    "context": ""
  },
  {
    "key": "MESPAK03_0011_0112",
    "original": "I lost the 'Farm Goods' \nsomewhere in Chip Forest.",
    "translation": "I lost the 'Farm Goods' \nsomewhere in Chip Forest.",
    "stage": 1,
    "context": ""
  },
  {
    "key": "MESPAK03_0011_0113",
    "original": "Are you ^P?\n\nWell, you see, I lost some very\nvaluable goods...\nHave you heard about \n'Farm Goods'?\nThey're important items used to\ntrain Digimon in the Farm.\nBut I must have dropped them\nsomewhere in Chip Forest.\nI'll make it worth your while if\nyou can go find them for me.\nSo could you go take a look?",
    "translation": "Are you ^P?\n\nWell, you see, I lost some very\nvaluable goods...\nHave you heard about \n'Farm Goods'?\nThey're important items used to\ntrain Digimon in the Farm.\nBut I must have dropped them\nsomewhere in Chip Forest.\nI'll make it worth your while if\nyou can go find them for me.\nSo could you go take a look?",
    "stage": 1,
    "context": ""
  },
  {
    "key": "MESPAK03_0011_0114",
    "original": "Thank you! With these, I can train\nand become stronger!\nHere, take these 'Farm Goods'\nas a reward!\n...Don't tell me you don't know\nhow to set them up??\nYou gotta at least know that much\nif you wanna be a Tamer!\nThen I'd better teach you!\n\nFirst, while in the DigiFarm,\nselect 'Manage Goods',\nFrom there, just choose which\ngoods you'd like to set!\nBy undergoing 'training' while\nusing those goods...\nYour Digimon will gradually\nbecome much stronger!\nGot that? Then good luck!\n",
    "translation": "Thank you! With these, I can train\nand become stronger!\nHere, take these 'Farm Goods'\nas a reward!\n...Don't tell me you don't know\nhow to set them up??\nYou gotta at least know that much\nif you wanna be a Tamer!\nThen I'd better teach you!\n\nFirst, while in the DigiFarm,\nselect 'Manage Goods',\nFrom there, just choose which\ngoods you'd like to set!\nBy undergoing 'training' while\nusing those goods...\nYour Digimon will gradually\nbecome much stronger!\nGot that? Then good luck!\n",
    "stage": 1,
    "context": ""
  },
  {
    "key": "MESPAK03_0011_0115",
    "original": "Obtained a Key Item!\nTanemon's Goods",
    "translation": "Obtained a Key Item!\nTanemon's Goods",
    "stage": 1,
    "context": ""
  },
  {
    "key": "MESPAK03_0011_0116",
    "original": "Uhmm...\nOkay, to set your Farm Goods...\nFirst, while in the DigiFarm,\nselect 'Manage Goods',\nFrom there, just choose which\ngoods you'd like to set!\nBy undergoing 'training' while\nusing those goods...\nYour Digimon will gradually\nbecome much stronger!\nGot that? Then good luck!",
    "translation": "Uhmm...\nOkay, to set your Farm Goods...\nFirst, while in the DigiFarm,\nselect 'Manage Goods',\nFrom there, just choose which\ngoods you'd like to set!\nBy undergoing 'training' while\nusing those goods...\nYour Digimon will gradually\nbecome much stronger!\nGot that? Then good luck!",
    "stage": 1,
    "context": ""
  },
  {
    "key": "MESPAK03_0011_0117",
    "original": "Obtained a Key Item!\nTanemon's Goods",
    "translation": "Obtained a Key Item!\nTanemon's Goods",
    "stage": 1,
    "context": ""
  },
  {
    "key": "MESPAK03_0011_0118",
    "original": "Yo, ^P!\nI've got a favor to ask of you!\nI'd like to deliver this lunchbox\nto my friend, Wormmon.\nThey're always working so hard!\n\nSo I made this lunchbox myself\nto help cheer them on!\nBut in order to reach Magnet\nMine, where Wormmon is,\nYou gotta travel underground...\n\nAnd you see, I don't have the\n'Dig' skill to do that...\nThat's why I'm here asking you!\n\nCould you please go to Magnet\nMine in my place?\nFirst, go to Login Mountain and\nask Armadillomon for digging tips!",
    "translation": "Yo, ^P!\nI've got a favor to ask of you!\nI'd like to deliver this lunchbox\nto my friend, Wormmon.\nThey're always working so hard!\n\nSo I made this lunchbox myself\nto help cheer them on!\nBut in order to reach Magnet\nMine, where Wormmon is,\nYou gotta travel underground...\n\nAnd you see, I don't have the\n'Dig' skill to do that...\nThat's why I'm here asking you!\n\nCould you please go to Magnet\nMine in my place?\nFirst, go to Login Mountain and\nask Armadillomon for digging tips!",
    "stage": 1,
    "context": ""
  },
  {
    "key": "MESPAK03_0011_0119",
    "original": "Obtained a key item!\nAgumon's Lunchbox",
    "translation": "Obtained a key item!\nAgumon's Lunchbox",
    "stage": 1,
    "context": ""
  },
  {
    "key": "MESPAK03_0011_0120",
    "original": "Armadillomon knows more about\nhow to use the 'Dig' skill,\nSo try asking them over at Login \nMountain!",
    "translation": "Armadillomon knows more about\nhow to use the 'Dig' skill,\nSo try asking them over at Login \nMountain!",
    "stage": 1,
    "context": ""
  },
  {
    "key": "MESPAK03_0011_0121",
    "original": "Armadillomon knows more about\nhow to use the 'Dig' skill,\nSo try asking them over at Login \nMountain!",
    "translation": "Armadillomon knows more about\nhow to use the 'Dig' skill,\nSo try asking them over at Login \nMountain!",
    "stage": 1,
    "context": ""
  },
  {
    "key": "MESPAK03_0011_0122",
    "original": "^P! Welcome back!\n...Are those...? \nWormmon's cookies?\n\nI'm super hungry right now, too!\n\nLooks like Wormmon's doing just\nfine, too...\nYou even brought their present\nback! Great work, Tamer!\nHere's your reward!\nThanks!",
    "translation": "^P! Welcome back!\n...Are those...? \nWormmon's cookies?\n\nI'm super hungry right now, too!\n\nLooks like Wormmon's doing just\nfine, too...\nYou even brought their present\nback! Great work, Tamer!\nHere's your reward!\nThanks!",
    "stage": 1,
    "context": ""
  },
  {
    "key": "MESPAK03_0011_0123",
    "original": "Handed over key item\nHandmade Cookies",
    "translation": "Handed over key item\nHandmade Cookies",
    "stage": 1,
    "context": ""
  },
  {
    "key": "MESPAK03_0011_0124",
    "original": "I'll ask for your help if I run into\nany trouble again.\nThanks again, ^P!\n",
    "translation": "I'll ask for your help if I run into\nany trouble again.\nThanks again, ^P!\n",
    "stage": 1,
    "context": ""
  },
  {
    "key": "MESPAK03_0011_0125",
    "original": "You want to know how to 'Dig'?\nI absolutely LOVE to dig!\nI want everyone in the world to \nunderstand the joys of digging!\nBut only certain kinds of Digimon\ncan use that skill.\nSo if you want to go digging\nunderground,\nYou'll need to have a Digimon\nwith the 'Dig' skill in your party.\nThe Dorumon around here\nhave the 'Dig' skill!\nRemember! The 'Dig' skill\nis a very valuable one!",
    "translation": "You want to know how to 'Dig'?\nI absolutely LOVE to dig!\nI want everyone in the world to \nunderstand the joys of digging!\nBut only certain kinds of Digimon\ncan use that skill.\nSo if you want to go digging\nunderground,\nYou'll need to have a Digimon\nwith the 'Dig' skill in your party.\nThe Dorumon around here\nhave the 'Dig' skill!\nRemember! The 'Dig' skill\nis a very valuable one!",
    "stage": 1,
    "context": ""
  },
  {
    "key": "MESPAK03_0011_0126",
    "original": "Dorumon possess the 'Dig' skill!\n\nYou wanna get to Magnet Mine?\n\nThen use that large hole thats at \nthe other end, it's just over there!",
    "translation": "Dorumon possess the 'Dig' skill!\n\nYou wanna get to Magnet Mine?\n\nThen use that large hole thats at \nthe other end, it's just over there!",
    "stage": 1,
    "context": ""
  },
  {
    "key": "MESPAK03_0011_0127",
    "original": "Hm? Do you need me for\nsomething?\nHm?!\n\nIs that the lunch box that\nAgumon prepared for me?!\nI see! So you've come to deliver\nit to me...\nThank you for taking the trouble\nto come all this way!\nI know! I'll give him these cookies\nI baked in return!\nYou said your name was \n^P, right?\nCould you please pass these\ncookies on to Agumon for me?\nI'd better take a break.\nTake care on your trip back!",
    "translation": "Hm? Do you need me for\nsomething?\nHm?!\n\nIs that the lunch box that\nAgumon prepared for me?!\nI see! So you've come to deliver\nit to me...\nThank you for taking the trouble\nto come all this way!\nI know! I'll give him these cookies\nI baked in return!\nYou said your name was \n^P, right?\nCould you please pass these\ncookies on to Agumon for me?\nI'd better take a break.\nTake care on your trip back!",
    "stage": 1,
    "context": ""
  },
  {
    "key": "MESPAK03_0011_0128",
    "original": "Handed over key item\nAgumon's Lunchbox",
    "translation": "Handed over key item\nAgumon's Lunchbox",
    "stage": 1,
    "context": ""
  },
  {
    "key": "MESPAK03_0011_0129",
    "original": "Obtained key item!\nHandmade Cookies",
    "translation": "Obtained key item!\nHandmade Cookies",
    "stage": 1,
    "context": ""
  },
  {
    "key": "MESPAK03_0011_0130",
    "original": "Munch munch...",
    "translation": "Munch munch...",
    "stage": 1,
    "context": ""
  },
  {
    "key": "MESPAK03_0011_0131",
    "original": "Hmmm...\nSo you're ^P?\nHey... Are you really as strong\nas they say you are...?\nEveryone's been making a big fuss\nbecause a Tamer showed up.\nBut I'd like to see the true extent\nof your abilities.\nIf you can use a 'Skill' to cut down \na tree \nThat's blocking the way to Label\nForest, then find a 'Leafy Branch'\nThen I'll acknowledge you as a\ntrue Tamer!\nPalmon's more familiar with how\nto use 'Skill's,\nSo I suggest you ask Palmon in\nLabel Forest about it, first.\nOh, that's right,\n\nYou'll need the address to Label\nForest to get there, won't you?\nThen here, take it.\n",
    "translation": "Hmmm...\nSo you're ^P?\nHey... Are you really as strong\nas they say you are...?\nEveryone's been making a big fuss\nbecause a Tamer showed up.\nBut I'd like to see the true extent\nof your abilities.\nIf you can use a 'Skill' to cut down \na tree \nThat's blocking the way to Label\nForest, then find a 'Leafy Branch'\nThen I'll acknowledge you as a\ntrue Tamer!\nPalmon's more familiar with how\nto use 'Skill's,\nSo I suggest you ask Palmon in\nLabel Forest about it, first.\nOh, that's right,\n\nYou'll need the address to Label\nForest to get there, won't you?\nThen here, take it.\n",
    "stage": 1,
    "context": ""
  },
  {
    "key": "MESPAK03_0011_0132",
    "original": "Obtained a Key item!\nLabel Forest Address",
    "translation": "Obtained a Key item!\nLabel Forest Address",
    "stage": 1,
    "context": ""
  },
  {
    "key": "MESPAK03_0011_0133",
    "original": "Got it?\n\nUse a 'Skill' to cut down a tree in\nLabel Forest.\nPalmon's more familiar with how\nto use 'Skill's,\nSo I suggest you ask Palmon in\nLabel Forest about it, first.",
    "translation": "Got it?\n\nUse a 'Skill' to cut down a tree in\nLabel Forest.\nPalmon's more familiar with how\nto use 'Skill's,\nSo I suggest you ask Palmon in\nLabel Forest about it, first.",
    "stage": 1,
    "context": ""
  },
  {
    "key": "MESPAK03_0011_0134",
    "original": "Hmmm...\nSo you're ^P?\nHey... Are you really as strong\nas they say you are...?\nEveryone's been making a big fuss\nbecause a Tamer showed up.\nBut I'd like to see the true extent\nof your abilities.\nIf you can use a 'Skill' to cut down \na tree \nThat's blocking the way to Label\nForest, then find a 'Leafy Branch'\nThen I'll acknowledge you as a\ntrue Tamer!\nPalmon's more familiar with how\nto use 'Skill's,\nSo I suggest you ask Palmon in\nLabel Forest about it, first.",
    "translation": "Hmmm...\nSo you're ^P?\nHey... Are you really as strong\nas they say you are...?\nEveryone's been making a big fuss\nbecause a Tamer showed up.\nBut I'd like to see the true extent\nof your abilities.\nIf you can use a 'Skill' to cut down \na tree \nThat's blocking the way to Label\nForest, then find a 'Leafy Branch'\nThen I'll acknowledge you as a\ntrue Tamer!\nPalmon's more familiar with how\nto use 'Skill's,\nSo I suggest you ask Palmon in\nLabel Forest about it, first.",
    "stage": 1,
    "context": ""
  },
  {
    "key": "MESPAK03_0011_0135",
    "original": "Wow, you really are something else.\n\nKeep this up and grow to become\na powerful Tamer!\nSkills are just the starting point, so\nwork hard and don't give up!\nHere's your reward. \nGo ahead and take it.",
    "translation": "Wow, you really are something else.\n\nKeep this up and grow to become\na powerful Tamer!\nSkills are just the starting point, so\nwork hard and don't give up!\nHere's your reward. \nGo ahead and take it.",
    "stage": 1,
    "context": ""
  },
  {
    "key": "MESPAK03_0011_0136",
    "original": "Handed over Key item\nLeafy Branch",
    "translation": "Handed over Key item\nLeafy Branch",
    "stage": 1,
    "context": ""
  },
  {
    "key": "MESPAK03_0011_0137",
    "original": "To tell the truth, I've always \nwanted to try using a Skill, myself.\nYou've gotta teach me someday!\n",
    "translation": "To tell the truth, I've always \nwanted to try using a Skill, myself.\nYou've gotta teach me someday!\n",
    "stage": 1,
    "context": ""
  },
  {
    "key": "MESPAK03_0011_0138",
    "original": "You want to know how to use\n'Skill's?\nOh, that's easy.\n\nAll you have to do is place a Digimon\nwith the required Skill in your party\nThen you can clear objects in your\nway without issue.\nI recall you saying something about\nneeding to cut down a tree, right?\nIn that case,\nYou'll need to bring a Digimon with\nthe skill 'Tree Cut'.\nLet's see... Hyokomon and \nFalcomon can use that skill!",
    "translation": "You want to know how to use\n'Skill's?\nOh, that's easy.\n\nAll you have to do is place a Digimon\nwith the required Skill in your party\nThen you can clear objects in your\nway without issue.\nI recall you saying something about\nneeding to cut down a tree, right?\nIn that case,\nYou'll need to bring a Digimon with\nthe skill 'Tree Cut'.\nLet's see... Hyokomon and \nFalcomon can use that skill!",
    "stage": 1,
    "context": ""
  },
  {
    "key": "MESPAK03_0011_0139",
    "original": "Let's see... \n\nHyokomon and Falcomon can use \nthe 'Tree Cut' skill!",
    "translation": "Let's see... \n\nHyokomon and Falcomon can use \nthe 'Tree Cut' skill!",
    "stage": 1,
    "context": ""
  },
  {
    "key": "MESPAK03_0011_0140",
    "original": "You did it! You successfully used\na 'Skill'!\nSkills are very important, so be\nsure to remember them!",
    "translation": "You did it! You successfully used\na 'Skill'!\nSkills are very important, so be\nsure to remember them!",
    "stage": 1,
    "context": ""
  },
  {
    "key": "MESPAK03_0011_0141",
    "original": "Obtained a Key item!\nLeafy Branch",
    "translation": "Obtained a Key item!\nLeafy Branch",
    "stage": 1,
    "context": ""
  },
  {
    "key": "MESPAK03_0011_0142",
    "original": "Seems there's been a mysterious \nshadow in Loop Swamp lately...\nI went to investigate, but turns out\nit was an Ebidramon.\nI heard rumors you were an \noutstanding Tamer, ^P.\nSo could you help make Ebidramon\nget out of the swamp?\nYou can only get to Loop Swamp\nby going underwater,\nSo you'll need a Digimon with\nthe 'Dive' skill.\nYou should go see Kamemon\nat Packet Coast first,\nAnd hear about using the 'Dive'\nskill.",
    "translation": "Seems there's been a mysterious \nshadow in Loop Swamp lately...\nI went to investigate, but turns out\nit was an Ebidramon.\nI heard rumors you were an \noutstanding Tamer, ^P.\nSo could you help make Ebidramon\nget out of the swamp?\nYou can only get to Loop Swamp\nby going underwater,\nSo you'll need a Digimon with\nthe 'Dive' skill.\nYou should go see Kamemon\nat Packet Coast first,\nAnd hear about using the 'Dive'\nskill.",
    "stage": 1,
    "context": ""
  },
  {
    "key": "MESPAK03_0011_0143",
    "original": "Please go to Loop Swamp using\nthe 'Dive' skill.\nYou should go see Kamemon\nat Packet Coast first,\nAnd hear about using the 'Dive'\nskill.",
    "translation": "Please go to Loop Swamp using\nthe 'Dive' skill.\nYou should go see Kamemon\nat Packet Coast first,\nAnd hear about using the 'Dive'\nskill.",
    "stage": 1,
    "context": ""
  },
  {
    "key": "MESPAK03_0011_0144",
    "original": "I see, so you helped Ebidramon\nunderstand the situation?\nNow everyone should feel safe \nagain. Thank you, ^P.\nGreat job! Here's your reward.",
    "translation": "I see, so you helped Ebidramon\nunderstand the situation?\nNow everyone should feel safe \nagain. Thank you, ^P.\nGreat job! Here's your reward.",
    "stage": 1,
    "context": ""
  },
  {
    "key": "MESPAK03_0011_0145",
    "original": "I hope you can help us out next \ntime we need it, too.",
    "translation": "I hope you can help us out next \ntime we need it, too.",
    "stage": 1,
    "context": ""
  },
  {
    "key": "MESPAK03_0011_0146",
    "original": "Diving underwater...?\n\nTo do that, you just gotta ride a\nDigimon with the 'Dive' skill.\nJust like that! Boing! Splosh!\nAnd there ya go!\nHm? Lunamon asked you to ask\nme about it...?\nYou could have said that earlier!\nAhem...!\nFirst you'll need to find a Digimon \nwith the 'Dive' skill...\nBetamon, for example. Then you\njust place them in your party.\nThen just go to any place with\na fountain spring and...\nDive right in!\nGive it a try!\nOf course, you'll need a Digimon\nwith the 'Dive' skill, first, though.",
    "translation": "Diving underwater...?\n\nTo do that, you just gotta ride a\nDigimon with the 'Dive' skill.\nJust like that! Boing! Splosh!\nAnd there ya go!\nHm? Lunamon asked you to ask\nme about it...?\nYou could have said that earlier!\nAhem...!\nFirst you'll need to find a Digimon \nwith the 'Dive' skill...\nBetamon, for example. Then you\njust place them in your party.\nThen just go to any place with\na fountain spring and...\nDive right in!\nGive it a try!\nOf course, you'll need a Digimon\nwith the 'Dive' skill, first, though.",
    "stage": 1,
    "context": ""
  },
  {
    "key": "MESPAK03_0011_0147",
    "original": "Betamon has the 'Dive' skill. You\ncan find them around this area.\nYou just gotta scan and convert\nthem...\nThere's a fountain near the sea, \nso you can just dive right in there.\nOh, and in Loop Swamp, there'll be\nwhirlpools you can use to travel, too.\nYou can go to another location just\nby approaching a big whirlpool!\nBut take note, you can't go back\nthrough a whirlpool you came from.\nSo be careful!",
    "translation": "Betamon has the 'Dive' skill. You\ncan find them around this area.\nYou just gotta scan and convert\nthem...\nThere's a fountain near the sea, \nso you can just dive right in there.\nOh, and in Loop Swamp, there'll be\nwhirlpools you can use to travel, too.\nYou can go to another location just\nby approaching a big whirlpool!\nBut take note, you can't go back\nthrough a whirlpool you came from.\nSo be careful!",
    "stage": 1,
    "context": ""
  },
  {
    "key": "MESPAK03_0011_0148",
    "original": "Wh-who are you...?\nHave you come to t-tease me...?\nI-I can be serious too, w-when \npush comes to shove...!",
    "translation": "Wh-who are you...?\nHave you come to t-tease me...?\nI-I can be serious too, w-when \npush comes to shove...!",
    "stage": 1,
    "context": ""
  },
  {
    "key": "MESPAK03_0011_0149",
    "original": "Ow ow ow...\n\nI-I was just hiding in the water \nbecause I'm a bit of a scaredy-cat.\nW-what's that...?\nA mysterious shadow...?\nI see... So I've been scaring \neveryone by accident...\nDid you say your name was\n^P...?\nCould you tell everyone they \ndon't need to be afraid...?\nI-I'll do my best to leave the\nwater, t-too...",
    "translation": "Ow ow ow...\n\nI-I was just hiding in the water \nbecause I'm a bit of a scaredy-cat.\nW-what's that...?\nA mysterious shadow...?\nI see... So I've been scaring \neveryone by accident...\nDid you say your name was\n^P...?\nCould you tell everyone they \ndon't need to be afraid...?\nI-I'll do my best to leave the\nwater, t-too...",
    "stage": 1,
    "context": ""
  },
  {
    "key": "MESPAK03_0011_0150",
    "original": "Help me let everyone know they \ndon't need to be afraid, okay...?",
    "translation": "Help me let everyone know they \ndon't need to be afraid, okay...?",
    "stage": 1,
    "context": ""
  },
  {
    "key": "MESPAK03_0011_0151",
    "original": "Hello, ^P, I've got a favor\nto ask of you.\nRecently, Dracmon's been playing\na lot of pranks.\nIt's been causing a lot of trouble\naround Packet Coast.\nCould you go teach them a lesson\nfor me...?",
    "translation": "Hello, ^P, I've got a favor\nto ask of you.\nRecently, Dracmon's been playing\na lot of pranks.\nIt's been causing a lot of trouble\naround Packet Coast.\nCould you go teach them a lesson\nfor me...?",
    "stage": 1,
    "context": ""
  },
  {
    "key": "MESPAK03_0011_0152",
    "original": "Dracmon especially likes to annoy\nme all the time.\nI really want to be friends with \nthem, so I wonder why...\nDracmon's pranks are causing\nproblems for everyone.\nSo please go to Packet Coast and\nteach them a lesson.",
    "translation": "Dracmon especially likes to annoy\nme all the time.\nI really want to be friends with \nthem, so I wonder why...\nDracmon's pranks are causing\nproblems for everyone.\nSo please go to Packet Coast and\nteach them a lesson.",
    "stage": 1,
    "context": ""
  },
  {
    "key": "MESPAK03_0011_0153",
    "original": "Welcome back, ^P!\nHow'd it go?\nI see, seems Dracmon isn't such\na bad guy,\nBut they just need some time to\ncool down, right?\nThank you for your help,\n^P.\nHere's your reward.\n",
    "translation": "Welcome back, ^P!\nHow'd it go?\nI see, seems Dracmon isn't such\na bad guy,\nBut they just need some time to\ncool down, right?\nThank you for your help,\n^P.\nHere's your reward.\n",
    "stage": 1,
    "context": ""
  },
  {
    "key": "MESPAK03_0011_0154",
    "original": "You're really reliable,\n^P.\nI'll be sure to let everyone know!\n",
    "translation": "You're really reliable,\n^P.\nI'll be sure to let everyone know!\n",
    "stage": 1,
    "context": ""
  },
  {
    "key": "MESPAK03_0011_0155",
    "original": "Hm?? What's that??\nYou got business with me??\nStop my pranks, you say?\nI'm causing trouble, you say??\nNo way! \nI'll do what I want!\nIf you insist! \nThen have a taste of my claws!",
    "translation": "Hm?? What's that??\nYou got business with me??\nStop my pranks, you say?\nI'm causing trouble, you say??\nNo way! \nI'll do what I want!\nIf you insist! \nThen have a taste of my claws!",
    "stage": 1,
    "context": ""
  },
  {
    "key": "MESPAK03_0011_0156",
    "original": "Hm?? What's this??\nWhy're you so strong??\nI-I just let my guard down, today!\nI'm actually much stronger!\nMy claws'll rip you to shreds one \nday, don't you forget it!",
    "translation": "Hm?? What's this??\nWhy're you so strong??\nI-I just let my guard down, today!\nI'm actually much stronger!\nMy claws'll rip you to shreds one \nday, don't you forget it!",
    "stage": 1,
    "context": ""
  },
  {
    "key": "MESPAK03_0011_0157",
    "original": "Whaddya want?!\nGet lost!\nI'll bite, you know! Grrrr!\n",
    "translation": "Whaddya want?!\nGet lost!\nI'll bite, you know! Grrrr!\n",
    "stage": 1,
    "context": ""
  },
  {
    "key": "MESPAK03_0011_0158",
    "original": "I just had a brilliant idea!\n\nI was just thinking of how to get\nyour name more out there!\nThat's when I thought of making\ncards!\nYou'll become super popular in\nno time, handing these out!\nCould you try handing out these\ntwo cards at Packet Coast?",
    "translation": "I just had a brilliant idea!\n\nI was just thinking of how to get\nyour name more out there!\nThat's when I thought of making\ncards!\nYou'll become super popular in\nno time, handing these out!\nCould you try handing out these\ntwo cards at Packet Coast?",
    "stage": 1,
    "context": ""
  },
  {
    "key": "MESPAK03_0011_0159",
    "original": "Obtained a key item!\nPopularity Card A",
    "translation": "Obtained a key item!\nPopularity Card A",
    "stage": 1,
    "context": ""
  },
  {
    "key": "MESPAK03_0011_0160",
    "original": "Obtained a key item!\nPopularity Card B",
    "translation": "Obtained a key item!\nPopularity Card B",
    "stage": 1,
    "context": ""
  },
  {
    "key": "MESPAK03_0011_0161",
    "original": "As for who...\nTanemon and Kokuwamon should\nbe at Packet Coast!\nTry giving out these two cards to\nthem!",
    "translation": "As for who...\nTanemon and Kokuwamon should\nbe at Packet Coast!\nTry giving out these two cards to\nthem!",
    "stage": 1,
    "context": ""
  },
  {
    "key": "MESPAK03_0011_0162",
    "original": "Great work, have you managed to\ngive both cards away...?\nThat's wonderful!\n\nNow everyone will acknowledge \nyou as a Tamer, I'm sure!\nHere's your reward! \nUse it wisely!",
    "translation": "Great work, have you managed to\ngive both cards away...?\nThat's wonderful!\n\nNow everyone will acknowledge \nyou as a Tamer, I'm sure!\nHere's your reward! \nUse it wisely!",
    "stage": 1,
    "context": ""
  },
  {
    "key": "MESPAK03_0011_0163",
    "original": "Everyone's been waiting for a\nTamer to arrive...\nI wish you luck from here on,\n^P.",
    "translation": "Everyone's been waiting for a\nTamer to arrive...\nI wish you luck from here on,\n^P.",
    "stage": 1,
    "context": ""
  },
  {
    "key": "MESPAK03_0011_0164",
    "original": "A popularity card?\nGuess I'll take one.\nWhoa, there's a lotta details here\nabout you, ^P.\nI'll be sure to come to you \nwhenever I need help.",
    "translation": "A popularity card?\nGuess I'll take one.\nWhoa, there's a lotta details here\nabout you, ^P.\nI'll be sure to come to you \nwhenever I need help.",
    "stage": 1,
    "context": ""
  },
  {
    "key": "MESPAK03_0011_0165",
    "original": "Handed over a key item\nPopularity Card A",
    "translation": "Handed over a key item\nPopularity Card A",
    "stage": 1,
    "context": ""
  },
  {
    "key": "MESPAK03_0011_0166",
    "original": "Maybe I should try making one of\nthese popularity cards, too...",
    "translation": "Maybe I should try making one of\nthese popularity cards, too...",
    "stage": 1,
    "context": ""
  },
  {
    "key": "MESPAK03_0011_0167",
    "original": "^P?\nI've heard about you...\nA popularity card...?\nSure, I'll take it...\nI'll approach you next time I \nrequire any assistance...\nThank you...\n",
    "translation": "^P?\nI've heard about you...\nA popularity card...?\nSure, I'll take it...\nI'll approach you next time I \nrequire any assistance...\nThank you...\n",
    "stage": 1,
    "context": ""
  },
  {
    "key": "MESPAK03_0011_0168",
    "original": "Handed over a key item\nPopularity Card B",
    "translation": "Handed over a key item\nPopularity Card B",
    "stage": 1,
    "context": ""
  },
  {
    "key": "MESPAK03_0011_0169",
    "original": "I'll be sure to come to you if I need\nany help in the future.",
    "translation": "I'll be sure to come to you if I need\nany help in the future.",
    "stage": 1,
    "context": ""
  },
  {
    "key": "MESPAK03_0011_0170",
    "original": "Hey, ^P,\nI've got a favor to ask.\nWell you see...\n\nBiyomon and I were supposed to \nhave a race at Label Forest.\nBut then I realized I haven't had\nany lunch yet.\nSo could you help me out, and\nlet Biyomon know I'll be late?",
    "translation": "Hey, ^P,\nI've got a favor to ask.\nWell you see...\n\nBiyomon and I were supposed to \nhave a race at Label Forest.\nBut then I realized I haven't had\nany lunch yet.\nSo could you help me out, and\nlet Biyomon know I'll be late?",
    "stage": 1,
    "context": ""
  },
  {
    "key": "MESPAK03_0011_0171",
    "original": "I can't unleash my full power on\nan empty stomach, after all.\nBiyomon's in Label Forest, please\nrelay my message to them.",
    "translation": "I can't unleash my full power on\nan empty stomach, after all.\nBiyomon's in Label Forest, please\nrelay my message to them.",
    "stage": 1,
    "context": ""
  },
  {
    "key": "MESPAK03_0011_0172",
    "original": "Munch munch...\nWelcome back, ^P.\nI see, so Biyomon's willing to wait\na little longer.\nHmmm...\nMaybe I should get some dessert?\nThank you, ^P.\n\nHere's your reward.\n",
    "translation": "Munch munch...\nWelcome back, ^P.\nI see, so Biyomon's willing to wait\na little longer.\nHmmm...\nMaybe I should get some dessert?\nThank you, ^P.\n\nHere's your reward.\n",
    "stage": 1,
    "context": ""
  },
  {
    "key": "MESPAK03_0011_0173",
    "original": "Hey, \nI've got both pudding and jelly...\nWhich do you think I should eat\nfirst, ^P?",
    "translation": "Hey, \nI've got both pudding and jelly...\nWhich do you think I should eat\nfirst, ^P?",
    "stage": 1,
    "context": ""
  },
  {
    "key": "MESPAK03_0011_0174",
    "original": "Jeez, just how long are they gonna\nmake me wait?! This is the worst!\nWhat? Patamon's gonna be late?\nBecause they're... eating lunch?!\nGrrrr! Now I'm angry!\nYou'd better look out!",
    "translation": "Jeez, just how long are they gonna\nmake me wait?! This is the worst!\nWhat? Patamon's gonna be late?\nBecause they're... eating lunch?!\nGrrrr! Now I'm angry!\nYou'd better look out!",
    "stage": 1,
    "context": ""
  },
  {
    "key": "MESPAK03_0011_0175",
    "original": "I'm so sorry!\nI let my anger take over!\nEven though Patamon's the \ncause of my anger...\nAh, but I feel much better after\nletting it all out.\nCould you go let Patamon know\nI'll wait for them!",
    "translation": "I'm so sorry!\nI let my anger take over!\nEven though Patamon's the \ncause of my anger...\nAh, but I feel much better after\nletting it all out.\nCould you go let Patamon know\nI'll wait for them!",
    "stage": 1,
    "context": ""
  },
  {
    "key": "MESPAK03_0011_0176",
    "original": "But only this once! Tell them it \nwon't happen again!",
    "translation": "But only this once! Tell them it \nwon't happen again!",
    "stage": 1,
    "context": ""
  },
  {
    "key": "MESPAK03_0011_0177",
    "original": "Greetings, ^P.\n\nI remember finding a positively\nbeautiful DigiFlower earlier...\nBut I've completely forgotten \nwhere it was.\nI'm pretty sure it was somewhere\naround Login Mountain.\nCould I trouble you to help me\nlook for it?",
    "translation": "Greetings, ^P.\n\nI remember finding a positively\nbeautiful DigiFlower earlier...\nBut I've completely forgotten \nwhere it was.\nI'm pretty sure it was somewhere\naround Login Mountain.\nCould I trouble you to help me\nlook for it?",
    "stage": 1,
    "context": ""
  },
  {
    "key": "MESPAK03_0011_0178",
    "original": "It was a very large pink and \nyellow flower!\nI remember seeing it somewhere\naround Login Mountain...\nCould I trouble you to help me look\nfor it?",
    "translation": "It was a very large pink and \nyellow flower!\nI remember seeing it somewhere\naround Login Mountain...\nCould I trouble you to help me look\nfor it?",
    "stage": 1,
    "context": ""
  },
  {
    "key": "MESPAK03_0011_0179",
    "original": "I see...\nSo it was a Sunflowmon...\nAnd it was so beautiful, too...\n\nI'm sorry to have troubled you\nwith this, ^P.\nBut I'm delighted that you did \nyour best to help look for it!\nIt's not much, but please take\nthis as a reward.",
    "translation": "I see...\nSo it was a Sunflowmon...\nAnd it was so beautiful, too...\n\nI'm sorry to have troubled you\nwith this, ^P.\nBut I'm delighted that you did \nyour best to help look for it!\nIt's not much, but please take\nthis as a reward.",
    "stage": 1,
    "context": ""
  },
  {
    "key": "MESPAK03_0011_0180",
    "original": "Still, the fact it was a Sunflowmon\nsure is a surprise.\nI was hoping to make it into a\npressed flower...\nBut I guess that's impossible now,\nsigh...",
    "translation": "Still, the fact it was a Sunflowmon\nsure is a surprise.\nI was hoping to make it into a\npressed flower...\nBut I guess that's impossible now,\nsigh...",
    "stage": 1,
    "context": ""
  },
  {
    "key": "MESPAK03_0011_0181",
    "original": "DigiFlower...?\nDid you say DigiFlower...?\nDamn it!\nI've had enough of this!\nEveryone keeps calling me a\nDigiFlower just because of my face!\nJust because my face is flower-\nshaped doesn't mean I'm a flower!\nApologize! NOW!!!",
    "translation": "DigiFlower...?\nDid you say DigiFlower...?\nDamn it!\nI've had enough of this!\nEveryone keeps calling me a\nDigiFlower just because of my face!\nJust because my face is flower-\nshaped doesn't mean I'm a flower!\nApologize! NOW!!!",
    "stage": 1,
    "context": ""
  },
  {
    "key": "MESPAK03_0011_0182",
    "original": "I give! I give!\nI've lost!\nYou sure are strong... Why are you\nlooking for a flower, anyway?\nGabumon was looking for it...?\n\nCome to think of it, I did see a \nGabumon looking at me before...\nGah!\n\nSo they also mistook me for a\nDigiFlower?!\nSo that's what happened!\nDamn it!\nGo tell Gabumon that they've got\nit all wrong, okay?!",
    "translation": "I give! I give!\nI've lost!\nYou sure are strong... Why are you\nlooking for a flower, anyway?\nGabumon was looking for it...?\n\nCome to think of it, I did see a \nGabumon looking at me before...\nGah!\n\nSo they also mistook me for a\nDigiFlower?!\nSo that's what happened!\nDamn it!\nGo tell Gabumon that they've got\nit all wrong, okay?!",
    "stage": 1,
    "context": ""
  },
  {
    "key": "MESPAK03_0011_0183",
    "original": "To think Gabumon mistook me for\na DigiFlower...\nTheir eyes must be broken or \nsomething!",
    "translation": "To think Gabumon mistook me for\na DigiFlower...\nTheir eyes must be broken or \nsomething!",
    "stage": 1,
    "context": ""
  },
  {
    "key": "MESPAK03_0011_0184",
    "original": "H-hello, ^P.\n\nDo you mind listening to my\nrequest?\nI... I've decided to enter the\nStone Contest...!\nBut I'm no good at making a\ndecision with my decorations...\nI'm thinking of using a DigiStone\nfrom Magnet Mine...!\nCould you please go get one for\nme, ^P?",
    "translation": "H-hello, ^P.\n\nDo you mind listening to my\nrequest?\nI... I've decided to enter the\nStone Contest...!\nBut I'm no good at making a\ndecision with my decorations...\nI'm thinking of using a DigiStone\nfrom Magnet Mine...!\nCould you please go get one for\nme, ^P?",
    "stage": 1,
    "context": ""
  },
  {
    "key": "MESPAK03_0011_0185",
    "original": "I heard that the DigiStones from\nMagnet Mine look really cool!\nIf I could get my hands on it, I'll\nwin the contest, no doubt!",
    "translation": "I heard that the DigiStones from\nMagnet Mine look really cool!\nIf I could get my hands on it, I'll\nwin the contest, no doubt!",
    "stage": 1,
    "context": ""
  },
  {
    "key": "MESPAK03_0011_0186",
    "original": "Welcome back, ^P!\n\nWhoa, it's a DigiStone!\nIt really does look super cool...!\nThank you so much! \nI'll win the contest for sure, now!\nOh yeah!\nI'd better give you your reward.\nThank you so much, really!\n",
    "translation": "Welcome back, ^P!\n\nWhoa, it's a DigiStone!\nIt really does look super cool...!\nThank you so much! \nI'll win the contest for sure, now!\nOh yeah!\nI'd better give you your reward.\nThank you so much, really!\n",
    "stage": 1,
    "context": ""
  },
  {
    "key": "MESPAK03_0011_0187",
    "original": "Handed over key item\nDigiStone",
    "translation": "Handed over key item\nDigiStone",
    "stage": 1,
    "context": ""
  },
  {
    "key": "MESPAK03_0011_0188",
    "original": "I just need to put this here, and \nthen do this, and... Yeah!\nI think it's going well... W-wow...\nThis is making me really nervous...",
    "translation": "I just need to put this here, and \nthen do this, and... Yeah!\nI think it's going well... W-wow...\nThis is making me really nervous...",
    "stage": 1,
    "context": ""
  },
  {
    "key": "MESPAK03_0011_0189",
    "original": "Who're you?!\nThis DigiStone is mine!\nThey're ALL mine!\nI won't give you a single pebble!",
    "translation": "Who're you?!\nThis DigiStone is mine!\nThey're ALL mine!\nI won't give you a single pebble!",
    "stage": 1,
    "context": ""
  },
  {
    "key": "MESPAK03_0011_0190",
    "original": "I just wanted to put these on so \nI could win the Stone Contest...\nThat's all...\n\nBut, I...\nI...!\nYou see, my body isn't actually\nmade of stone!\nSo fine, I'll give one to you!\n",
    "translation": "I just wanted to put these on so \nI could win the Stone Contest...\nThat's all...\n\nBut, I...\nI...!\nYou see, my body isn't actually\nmade of stone!\nSo fine, I'll give one to you!\n",
    "stage": 1,
    "context": ""
  },
  {
    "key": "MESPAK03_0011_0191",
    "original": "Obtained a key item!\nDigiStone",
    "translation": "Obtained a key item!\nDigiStone",
    "stage": 1,
    "context": ""
  },
  {
    "key": "MESPAK03_0011_0192",
    "original": "Next time, remember when there's\na contest, okay?!",
    "translation": "Next time, remember when there's\na contest, okay?!",
    "stage": 1,
    "context": ""
  },
  {
    "key": "MESPAK03_0011_0193",
    "original": "I wish I could enter it...\nThat Stone Contest...",
    "translation": "I wish I could enter it...\nThat Stone Contest...",
    "stage": 1,
    "context": ""
  },
  {
    "key": "MESPAK03_0011_0194",
    "original": "T-this is terrible!\n^P!\nA distant relative of mine entrusted\nme with their child, but...\nT-the child... has gone missing!\n\nWha...? T-their name...?\nTheir name is Chicchimon...\nThey've mentioned before that\nthey'd like to see Loop Swamp...\nDon't tell me...\nPlease, could you go take a look?",
    "translation": "T-this is terrible!\n^P!\nA distant relative of mine entrusted\nme with their child, but...\nT-the child... has gone missing!\n\nWha...? T-their name...?\nTheir name is Chicchimon...\nThey've mentioned before that\nthey'd like to see Loop Swamp...\nDon't tell me...\nPlease, could you go take a look?",
    "stage": 1,
    "context": ""
  },
  {
    "key": "MESPAK03_0011_0195",
    "original": "Chicchimon wanted to go to\nLoop Swamp...\nSo they may have gone there\nall by themself...\nThe whirlpools at Loop Swamp let\nyou travel from one place to another\nYou can move to another area by\napproaching a big whirlpool.\nBut you can't go back through a\nwhirlpool you've come through.\nS-so, please be careful...",
    "translation": "Chicchimon wanted to go to\nLoop Swamp...\nSo they may have gone there\nall by themself...\nThe whirlpools at Loop Swamp let\nyou travel from one place to another\nYou can move to another area by\napproaching a big whirlpool.\nBut you can't go back through a\nwhirlpool you've come through.\nS-so, please be careful...",
    "stage": 1,
    "context": ""
  },
  {
    "key": "MESPAK03_0011_0196",
    "original": "Oh! ^P!\nDid you find Chicchimon?\nI-I see, so they're okay...\n\nI'll be sure to keep a closer eye on\nthem from now on!\nHere's your reward, as promised!\nThank you so much, ^P!",
    "translation": "Oh! ^P!\nDid you find Chicchimon?\nI-I see, so they're okay...\n\nI'll be sure to keep a closer eye on\nthem from now on!\nHere's your reward, as promised!\nThank you so much, ^P!",
    "stage": 1,
    "context": ""
  },
  {
    "key": "MESPAK03_0011_0197",
    "original": "Chicchimon wanders all over the \nplace, so it's difficult to keep up...\nBut thanks to you, ^P,\nwe were able to find them.",
    "translation": "Chicchimon wanders all over the \nplace, so it's difficult to keep up...\nBut thanks to you, ^P,\nwe were able to find them.",
    "stage": 1,
    "context": ""
  },
  {
    "key": "MESPAK03_0011_0198",
    "original": "Wheeee!\nSpinning around is so much fun!\nHmm??\nDo you need me for something?\nUncle Hawkmon is looking for me...?\n\nJeez!\nHe's always treating me like a child!\nBut I guess I shouldn't have\nwandered off without a word...\nI'll have to go apologize later!\nThanks for checking on me!",
    "translation": "Wheeee!\nSpinning around is so much fun!\nHmm??\nDo you need me for something?\nUncle Hawkmon is looking for me...?\n\nJeez!\nHe's always treating me like a child!\nBut I guess I shouldn't have\nwandered off without a word...\nI'll have to go apologize later!\nThanks for checking on me!",
    "stage": 1,
    "context": ""
  },
  {
    "key": "MESPAK03_0011_0199",
    "original": "Uncle Hawkmon can be such a\nworrywart sometimes!",
    "translation": "Uncle Hawkmon can be such a\nworrywart sometimes!",
    "stage": 1,
    "context": ""
  }
]